pypyrslack/__init__.py
pypyrslack/errors.py
pypyrslack/version.py
pypyrslack/steps/__init__.py
pypyrslack/steps/send.py
pypyrslack-1.2.0.dist-info/LICENSE
pypyrslack-1.2.0.dist-info/METADATA
pypyrslack-1.2.0.dist-info/WHEEL
pypyrslack-1.2.0.dist-info/top_level.txt
pypyrslack-1.2.0.dist-info/RECORD
