Metadata-Version: 2.1
Name: pypyrslack
Version: 1.2.0
Summary: pypyr slack plug-in: send slack messages & notifications from pypyr task-runner automation pipelines.
Home-page: https://pypyr.io/
Author: Thomas Gaigher
Author-email: info@pypyr.io
License: Apache License 2.0
Project-URL: Documentation, https://pypyr.io/docs/plugins/slack/
Project-URL: Source, https://github.com/pypyr/pypyr-slack
Project-URL: Release notes, https://pypyr.io/updates/releases/
Project-URL: Tracker, https://github.com/pypyr/pypyr-slack/issues/
Keywords: pypyr,slack,plugin,devops,task-runner,pipeline
Platform: UNKNOWN
Classifier: Development Status :: 5 - Production/Stable
Classifier: Intended Audience :: Developers
Classifier: Topic :: Software Development :: Build Tools
Classifier: Topic :: Software Development :: Libraries :: Python Modules
Classifier: License :: OSI Approved :: Apache Software License
Classifier: Programming Language :: Python :: 3.7
Classifier: Programming Language :: Python :: 3.8
Classifier: Programming Language :: Python :: 3.9
Classifier: Programming Language :: Python :: 3.10
License-File: LICENSE
Requires-Dist: pypyr
Requires-Dist: slackclient
Provides-Extra: dev
Requires-Dist: bumpversion ; extra == 'dev'
Requires-Dist: codecov ; extra == 'dev'
Requires-Dist: flake8 ; extra == 'dev'
Requires-Dist: flake8-docstrings ; extra == 'dev'
Requires-Dist: pypyr ; extra == 'dev'
Requires-Dist: pytest ; extra == 'dev'
Requires-Dist: pytest-cov ; extra == 'dev'
Requires-Dist: setuptools ; extra == 'dev'
Requires-Dist: twine ; extra == 'dev'
Requires-Dist: wheel ; extra == 'dev'
